ezSMS/__init__.py
ezSMS/errors.py
ezSMS/messenger.py
ezSMS-0.3.0.dist-info/LICENSE
ezSMS-0.3.0.dist-info/METADATA
ezSMS-0.3.0.dist-info/WHEEL
ezSMS-0.3.0.dist-info/top_level.txt
ezSMS-0.3.0.dist-info/RECORD
