Metadata-Version: 2.1
Name: ezSMS
Version: 0.3.0
Summary: A small package that allows you to send easy SMS messages.
Home-page: https://github.com/TilakPatel/pypi-easy-sms
Author: Tilak Patel
Author-email: tilakpat@outlook.com
License: UNKNOWN
Platform: UNKNOWN
Classifier: Programming Language :: Python :: 3
Classifier: License :: OSI Approved :: MIT License
Classifier: Operating System :: OS Independent
Requires-Python: >=3.6
